sphi_sola/__init__.py
sphi_sola/_version.py
sphi_sola/layout.html
sphi_sola/theme.conf
sphi_sola/static/Ubuntu.woff2
sphi_sola/static/UbuntuMono.woff2
sphi_sola/static/alert_info_32.png
sphi_sola/static/alert_warning_32.png
sphi_sola/static/bullet_orange.png
sphi_sola/static/logo.png
sphi_sola/static/sphi_sola.css_t
sphi_sola-0.1.2.dist-info/LICENSE
sphi_sola-0.1.2.dist-info/METADATA
sphi_sola-0.1.2.dist-info/WHEEL
sphi_sola-0.1.2.dist-info/entry_points.txt
sphi_sola-0.1.2.dist-info/top_level.txt
sphi_sola-0.1.2.dist-info/RECORD
