Metadata-Version: 2.1
Name: sphi-sola
Version: 0.1.2
Summary: Sphinx theme based on Solarized colour scheme.
Home-page: https://github.com/matthias-stein/sphi_sola
Author: Matthias Stein
Author-email: git.matthias@gmail.com
License: UNKNOWN
Platform: UNKNOWN
Requires-Dist: sphinx (>=1.6)
Requires-Dist: pygments-style-solarized (==0.1.1)
